django_dzenlog
