Metadata-Version: 1.0
Name: django-dzenlog
Version: 0.3.0
Summary: Django Dzenlog is a set of models and templates, which can be used to create blogs with different kinds media.
Home-page: http://github.com/svetlyak40wt/django-dzenlog/
Author: Alexander Artemenko
Author-email: svetlyak.40wt@gmail.com
License: New BSD License
Keywords: django apps blogging
Platform: UNKNOWN
Classifier: Development Status :: 3 - Alpha
Classifier: Environment :: Plugins
Classifier: Framework :: Django
Classifier: Intended Audience :: Developers
Classifier: License :: OSI Approved :: BSD License
Classifier: Programming Language :: Python
Classifier: Topic :: Software Development :: Libraries :: Python Modules
